bettermt5/__init__.py
bettermt5/core.py
bettermt5-0.0.7.dist-info/licenses/LICENSE
bettermt5-0.0.7.dist-info/METADATA
bettermt5-0.0.7.dist-info/WHEEL
bettermt5-0.0.7.dist-info/top_level.txt
bettermt5-0.0.7.dist-info/RECORD
